{
    "simulation" : {
        "coopratioPhase2" : 1,
        "coopratioPhase3" : 0,
        "headless" : true,
        "parkingspaces" : {
            "free" : 15,
            "total" : 576
        },
        "resourcedir" : "resources",
        "routefile" : "reroute-s5-p15-c1-0-r500.rou.xml",
        "runconfiguration" : "config-s5-p15-c1-0-r500.runs.json.gz",
        "runs" : 500,
        "sumoport" : 9068,
        "vehicles" : 5
    },
    "vehicle" : {
        "maxspeed" : {
            "phase1" : 27.778,
            "phase2" : 8.333,
            "phase3" : 8.333
        },
        "parking" : {
            "distance" : {
                "max" : 30.0,
                "min" : 12.0
            },
            "duration" : 12.0
        },
        "phase3randomprob" : 0.0,
        "weights" : {
            "coop" : {
                "distance" : 1,
                "externalplanned" : 100,
                "externalvisit" : 2000,
                "selfvisit" : 2000
            },
            "noncoop" : {
                "distance" : 1,
                "externalplanned" : 0,
                "externalvisit" : 0,
                "selfvisit" : 2000
            }
        }
    }
}
